mtchrs/__init__.py
mtchrs/matchers.py
mtchrs-0.1.1.dist-info/licenses/LICENSE
mtchrs-0.1.1.dist-info/METADATA
mtchrs-0.1.1.dist-info/WHEEL
mtchrs-0.1.1.dist-info/top_level.txt
mtchrs-0.1.1.dist-info/RECORD
